portfolio_tracker_cli/__init__.py
portfolio_tracker_cli/portfolio_cli.py
portfolio_tracker_cli-1.0.0.dist-info/METADATA
portfolio_tracker_cli-1.0.0.dist-info/WHEEL
portfolio_tracker_cli-1.0.0.dist-info/entry_points.txt
portfolio_tracker_cli-1.0.0.dist-info/top_level.txt
portfolio_tracker_cli-1.0.0.dist-info/RECORD
