Metadata-Version: 2.1
Name: portfolio-tracker-cli
Version: 1.0.0
Summary: A professional command-line tool for tracking crypto and stock investments
Home-page: https://github.com/yangwl356/portfolio-tracker-cli
Author: Yangwl356
Author-email: yangwl356@proton.me
Project-URL: Bug Reports, https://github.com/yangwl356/portfolio-tracker-cli/issues
Project-URL: Source, https://github.com/yangwl356/portfolio-tracker-cli
Project-URL: Documentation, https://github.com/yangwl356/portfolio-tracker-cli#readme
Keywords: portfolio,crypto,stocks,investment,tracking,cli,finance
Classifier: Development Status :: 4 - Beta
Classifier: Intended Audience :: Financial and Insurance Industry
Classifier: License :: OSI Approved :: MIT License
Classifier: Operating System :: OS Independent
Classifier: Programming Language :: Python :: 3
Classifier: Programming Language :: Python :: 3.7
Classifier: Programming Language :: Python :: 3.8
Classifier: Programming Language :: Python :: 3.9
Classifier: Programming Language :: Python :: 3.10
Classifier: Programming Language :: Python :: 3.11
Classifier: Topic :: Office/Business :: Financial :: Investment
Classifier: Topic :: Software Development :: Libraries :: Python Modules
Requires-Python: >=3.7
Requires-Dist: pandas (>=1.3.0)
Requires-Dist: requests (>=2.25.0)
Requires-Dist: rich (>=10.0.0)
